pyQParamWidget/LICENSE.txt
pyQParamWidget/__init__.py
pyQParamWidget/_version.py
pyQParamWidget/param_editor.py
pyQParamWidget/param_editor.ui
pyQParamWidget/param_item.py
pyQParamWidget/param_tree.py
pyQParamWidget/param_tree.ui
pyQParamWidget/qpw_widgets.py
pyQParamWidget/utils.py
pyQParamWidget/tests/__init__.py
pyQParamWidget/tests/test_true.py
pyQParamWidget-0.1.0.dist-info/METADATA
pyQParamWidget-0.1.0.dist-info/WHEEL
pyQParamWidget-0.1.0.dist-info/top_level.txt
pyQParamWidget-0.1.0.dist-info/RECORD
