Metadata-Version: 2.1
Name: pyQParamWidget
Version: 0.1.0
Summary: A PyQt5 editor (QWidget) and tree (QDialog) to edit application parameters.
Author-email: Pete Jemian <prjemian+pyQParamWidget@gmail.com>
Maintainer-email: Pete Jemian <prjemian+pyQParamWidget@gmail.com>
License: Creative Commons Attribution 4.0 International Public License
Project-URL: Homepage, https://prjemian.github.io/pyQParamWidget/
Project-URL: Bug Tracker, https://github.com/prjemian/pyQParamWidget/issues
Keywords: PyQt,editor
Classifier: Development Status :: 3 - Alpha
Classifier: Intended Audience :: Developers
Classifier: License :: Freely Distributable
Classifier: License :: Public Domain
Classifier: Programming Language :: Python
Classifier: Programming Language :: Python :: 3
Classifier: Programming Language :: Python :: 3.10
Classifier: Programming Language :: Python :: 3.11
Classifier: Programming Language :: Python :: 3.12
Classifier: Topic :: Software Development
Requires-Python: >=3.10
Requires-Dist: PyQt5
